buildpy/v1/__init__.py
buildpy/v2/__init__.py
buildpy/v3/__init__.py
buildpy/v4/__init__.py
buildpy/v5/__init__.py
buildpy/v5/_convenience/__init__.py
buildpy/v5/_log/__init__.py
buildpy/v5/_tval/__init__.py
buildpy/v5/exception/__init__.py
buildpy/v5/resource/__init__.py
buildpy/v6/__init__.py
buildpy/v6/_convenience/__init__.py
buildpy/v6/_log/__init__.py
buildpy/v6/_tval/__init__.py
buildpy/v6/exception/__init__.py
buildpy/v6/resource/__init__.py
buildpy/v7/__init__.py
buildpy/v7/_convenience/__init__.py
buildpy/v7/_log/__init__.py
buildpy/v7/_tval/__init__.py
buildpy/v7/exception/__init__.py
buildpy/v7/resource/__init__.py
buildpy/v8/__init__.py
buildpy/v8/_convenience/__init__.py
buildpy/v8/_log/__init__.py
buildpy/v8/_tval/__init__.py
buildpy/v8/exception/__init__.py
buildpy/v8/resource/__init__.py
buildpy/v9/__init__.py
buildpy/v9/_convenience/__init__.py
buildpy/v9/_log/__init__.py
buildpy/v9/_tval/__init__.py
buildpy/v9/exception/__init__.py
buildpy/v9/resource/__init__.py
buildpy/vx/__init__.py
buildpy/vx/_convenience/__init__.py
buildpy/vx/_log/__init__.py
buildpy/vx/_tval/__init__.py
buildpy/vx/exception/__init__.py
buildpy/vx/resource/__init__.py
buildpy-9.4.0.data/data/LICENSE.txt
buildpy-9.4.0.dist-info/LICENSE.txt
buildpy-9.4.0.dist-info/METADATA
buildpy-9.4.0.dist-info/WHEEL
buildpy-9.4.0.dist-info/top_level.txt
buildpy-9.4.0.dist-info/zip-safe
buildpy-9.4.0.dist-info/RECORD
